{
	"textures": [
		{
			"image": "recycling",
			"format": "RGBA8888",
			"size": {
				"w": 110,
				"h": 62
			},
			"scale": 1,
			"frames": [
				{
					"filename": "screen",
					"rotated": false,
					"trimmed": false,
					"sourceSize": {
						"w": 30,
						"h": 32
					},
					"spriteSourceSize": {
						"x": 0,
						"y": 0,
						"w": 30,
						"h": 32
					},
					"frame": {
						"x": 0,
						"y": 0,
						"w": 30,
						"h": 32
					}
				},
				{
					"filename": "laptop",
					"rotated": false,
					"trimmed": false,
					"sourceSize": {
						"w": 40,
						"h": 28
					},
					"spriteSourceSize": {
						"x": 0,
						"y": 0,
						"w": 40,
						"h": 28
					},
					"frame": {
						"x": 0,
						"y": 32,
						"w": 40,
						"h": 28
					}
				},
				{
					"filename": "console1",
					"rotated": false,
					"trimmed": false,
					"sourceSize": {
						"w": 40,
						"h": 19
					},
					"spriteSourceSize": {
						"x": 0,
						"y": 0,
						"w": 40,
						"h": 19
					},
					"frame": {
						"x": 30,
						"y": 0,
						"w": 40,
						"h": 19
					}
				},
				{
					"filename": "phone",
					"rotated": false,
					"trimmed": false,
					"sourceSize": {
						"w": 14,
						"h": 24
					},
					"spriteSourceSize": {
						"x": 0,
						"y": 0,
						"w": 14,
						"h": 24
					},
					"frame": {
						"x": 40,
						"y": 19,
						"w": 14,
						"h": 24
					}
				},
				{
					"filename": "console2",
					"rotated": false,
					"trimmed": false,
					"sourceSize": {
						"w": 40,
						"h": 19
					},
					"spriteSourceSize": {
						"x": 0,
						"y": 0,
						"w": 40,
						"h": 19
					},
					"frame": {
						"x": 40,
						"y": 43,
						"w": 40,
						"h": 19
					}
				},
				{
					"filename": "console3",
					"rotated": false,
					"trimmed": false,
					"sourceSize": {
						"w": 40,
						"h": 19
					},
					"spriteSourceSize": {
						"x": 0,
						"y": 0,
						"w": 40,
						"h": 19
					},
					"frame": {
						"x": 70,
						"y": 0,
						"w": 40,
						"h": 19
					}
				},
				{
					"filename": "console4",
					"rotated": false,
					"trimmed": false,
					"sourceSize": {
						"w": 40,
						"h": 19
					},
					"spriteSourceSize": {
						"x": 0,
						"y": 0,
						"w": 40,
						"h": 19
					},
					"frame": {
						"x": 54,
						"y": 19,
						"w": 40,
						"h": 19
					}
				}
			]
		}
	],
	"meta": {
		"app": "http://free-tex-packer.com",
		"version": "0.6.7"
	}
}